mqt_ddsim-2.1.0.dist-info/RECORD
mqt_ddsim-2.1.0.dist-info/WHEEL
mqt_ddsim-2.1.0.dist-info/METADATA
mqt_ddsim-2.1.0.dist-info/licenses/LICENSE.md
mqt/ddsim/statevector_simulator_backend.py
mqt/ddsim/experiment_header.py
mqt/ddsim/pyddsim.cpython-310-darwin.so
mqt/ddsim/deterministic_noise_simulator_backend.py
mqt/ddsim/unitary_simulator_backend.py
mqt/ddsim/_version.pyi
mqt/ddsim/provider.py
mqt/ddsim/path_statevector_simulator_backend.py
mqt/ddsim/_version.py
mqt/ddsim/job.py
mqt/ddsim/pyddsim.pyi
mqt/ddsim/__init__.py
mqt/ddsim/hybrid_statevector_simulator_backend.py
mqt/ddsim/qasm_simulator_backend.py
mqt/ddsim/stochastic_noise_simulator_backend.py
mqt/ddsim/py.typed
mqt/ddsim/target.py
mqt/ddsim/path_qasm_simulator_backend.py
mqt/ddsim/hybrid_qam_simulator_backend.py
mqt/ddsim/primitives/__init__.py
mqt/ddsim/primitives/estimator.py
mqt/ddsim/primitives/sampler.py
