Metadata-Version: 2.4
Name: mqt.ddsim
Version: 2.1.0
Summary: A quantum simulator based on decision diagrams written in C++
Keywords: MQT,quantum-computing,design-automation,quantum-circuit-sim,simulation
Author-Email: Lukas Burgholzer <lukas.burgholzer@tum.de>, Stefan Hillmich <stefan.hillmich@scch.at>
License-Expression: MIT
License-File: LICENSE.md
Classifier: Topic :: Scientific/Engineering :: Electronic Design Automation (EDA)
Classifier: Intended Audience :: Science/Research
Classifier: Natural Language :: English
Classifier: Operating System :: POSIX :: Linux
Classifier: Operating System :: MacOS
Classifier: Operating System :: Microsoft :: Windows
Classifier: Programming Language :: C++
Classifier: Programming Language :: Python
Classifier: Programming Language :: Python :: 3
Classifier: Programming Language :: Python :: 3 :: Only
Classifier: Programming Language :: Python :: 3.10
Classifier: Programming Language :: Python :: 3.11
Classifier: Programming Language :: Python :: 3.12
Classifier: Programming Language :: Python :: 3.13
Classifier: Programming Language :: Python :: 3.14
Classifier: Development Status :: 5 - Production/Stable
Project-URL: Homepage, https://github.com/munich-quantum-toolkit/ddsim
Project-URL: Documentation, https://mqt.readthedocs.io/projects/ddsim
Project-URL: Issues, https://github.com/munich-quantum-toolkit/ddsim/issues
Project-URL: Discussions, https://github.com/munich-quantum-toolkit/ddsim/discussions
Requires-Python: >=3.10
Requires-Dist: mqt.core[qiskit]~=3.3.1
Requires-Dist: qiskit>=1.1
